[{"id":"a1","firstName":"אורי","lastName":"שרייבר","name":"אורי שרייבר","accessLevel":0,"profile":"3","cell":"052 4402515","phone":"052 4402515","email":"ori.schreiber@gmail.com","password":"12345678","confirmpass":"12345678","departments":[],"orgs":[],"updated":"2017-08-06T04:42:32.4876413Z","updatedBy":"Moishe Schreiber"},{"id":"a2","firstName":"יאיר","lastName":"גת","name":"יאיר גת","accessLevel":1,"profile":"1","cell":"052 4402515","phone":"052 4402515","email":"ori.schreiber@gmail.com","password":"12345678","confirmpass":"12345678","orgs":[],"departments":[],"updated":"2017-08-06T04:42:26.8306906Z","updatedBy":"Moishe Schreiber"},{"id":"a3","firstName":"מושה","lastName":"לוי","name":"מושה לוי","accessLevel":2,"profile":"2","cell":"052 4402515","phone":"052 4402515","email":"ori.schreiber@gmail.com","password":"12345678","confirmpass":"12345678","departments":[],"orgs":[],"updated":"2017-08-06T04:42:19.4220294Z","updatedBy":"Moishe Schreiber"},{"id":"a4","firstName":"יעל","lastName":"שצמן","name":"יעל שצמן","accessLevel":0,"profile":"3","cell":"052 4402515","phone":"052 4402515","email":"ori.schreiber@gmail.com","password":"12345678","confirmpass":"12345678","orgs":[],"departments":[{"id":"a3","name":"מחלקה שלישית","accessLevel":"U"}],"updated":"2017-08-06T04:39:11.4098199Z","updatedBy":"Moishe Schreiber"},{"id":"a5","firstName":"קרן","lastName":"שצמו","name":"קרן שצמו","accessLevel":1,"profile":"1","cell":"052 4402515","phone":"052 4402515","email":"ori.schreiber@gmail.com","password":"12345678","confirmpass":"12345678","orgs":[],"departments":[],"updated":"2017-08-06T04:42:12.8815805Z","updatedBy":"Moishe Schreiber"}]